tdameritrade_client/__init__.py
tdameritrade_client/auth.py
tdameritrade_client/client.py
tdameritrade_client/utils/__init__.py
tdameritrade_client/utils/create_certs.py
tdameritrade_client/utils/tools.py
tdameritrade_client/utils/urls.py
tdameritrade_client-0.5.0.dist-info/LICENSE
tdameritrade_client-0.5.0.dist-info/WHEEL
tdameritrade_client-0.5.0.dist-info/METADATA
tdameritrade_client-0.5.0.dist-info/RECORD
