Metadata-Version: 2.1
Name: tdameritrade-client
Version: 0.5.0
Summary: A client for the TDA API
Home-page: https://gitlab.com/tdameritrade-tools/tdameritrade-client
Author: Joe Castagneri
Author-email: jcastagneri@gmail.com
Requires-Python: >=3.6,<4.0
Classifier: License :: OSI Approved :: MIT License
Classifier: Operating System :: MacOS
Classifier: Operating System :: Microsoft :: Windows
Classifier: Operating System :: POSIX :: Linux
Classifier: Programming Language :: Python :: 3
Classifier: Programming Language :: Python :: 3.6
Classifier: Programming Language :: Python :: 3.7
Requires-Dist: environs (>=4.1,<5.0)
Requires-Dist: pyopenssl (>=19.0,<20.0)
Requires-Dist: requests (>=2.21,<3.0)
Project-URL: Documentation, https://tdameritrade-client.readthedocs.io/en/latest/?#
Project-URL: Repository, https://gitlab.com/tdameritrade-tools/tdameritrade-client
